sphinx_astrorefs/__init__.py
sphinx_astrorefs/pybtex_astro.py
sphinx_astrorefs/reformat.py
sphinx_astrorefs/resolve_aas.py
sphinx_astrorefs/_static/sphinx_astrorefs.css
sphinx_astrorefs-0.15.dist-info/LICENSE
sphinx_astrorefs-0.15.dist-info/METADATA
sphinx_astrorefs-0.15.dist-info/WHEEL
sphinx_astrorefs-0.15.dist-info/top_level.txt
sphinx_astrorefs-0.15.dist-info/RECORD
