Metadata-Version: 2.2
Name: sphinx-astrorefs
Version: 0.15
Summary: Astro-style references in Sphinx documents
Author: Jo Bovy
Author-email: bovy@astro.utoronto.ca
License: MIT
License-File: LICENSE
Requires-Dist: sphinx
Requires-Dist: sphinxcontrib-bibtex==2.1.4
Requires-Dist: pybtex
Requires-Dist: latexcodec
Dynamic: author
Dynamic: author-email
Dynamic: description
Dynamic: description-content-type
Dynamic: license
Dynamic: requires-dist
Dynamic: summary
